{"object": "list", "results": [{"object": "page", "id": "da6b77aa-3418-4bc7-99c1-3a4852df7e42", "created_time": "2021-11-07T02:43:00.000Z", "last_edited_time": "2021-11-07T02:44:00.000Z", "cover": null, "icon": null, "parent": {"type": "database_id", "database_id": "52086760-ffa9-405a-ade3-a6b00bad1834"}, "archived": false, "properties": {"# worn": {"id": "B%3DFg", "type": "number", "number": 0}, "Not so much 💔": {"id": "G%3Ar%3D", "type": "checkbox", "checkbox": false}, "Brand": {"id": "IhVC", "type": "multi_select", "multi_select": [{"id": "ce49bd64-7c71-4e9c-b22f-e150ec530652", "name": "thrifted 🌱", "color": "green"}]}, "Occasion": {"id": "PbHh", "type": "multi_select", "multi_select": [{"id": "71b4c590-a3bd-427a-821d-e4b87ddab06d", "name": "cute", "color": "orange"}, {"id": "4a2ef721-6f0b-4163-bee2-bd4239d74343", "name": "summer", "color": "pink"}, {"id": "a2f57cee-d198-45b4-a451-778e7eecb804", "name": "versatile", "color": "green"}]}, "Color": {"id": "%5B%3D%7B%3F", "type": "multi_select", "multi_select": [{"id": "e816ffbd-4c0a-4667-a3e7-8a1169be47d8", "name": "light pink", "color": "brown"}]}, "Photo": {"id": "l%5DHF", "type": "files", "files": [{"name": "pink tank top.png", "type": "file", "file": {"url": "https://s3.us-west-2.amazonaws.com/secure.notion-static.com/a0bfeb19-4655-4305-8418-bfb09e0c83c7/pink_tank_top.png?X-Amz-Algorithm=AWS4-HMAC-SHA256&X-Amz-Credential=AKIAT73L2G45O3KS52Y5%2F20211107%2Fus-west-2%2Fs3%2Faws4_request&X-Amz-Date=20211107T030618Z&X-Amz-Expires=3600&X-Amz-Signature=d6e860c1454a4a1af9f9b0ca00a100994e2475789916b6f83c6ddc64ba873f29&X-Amz-SignedHeaders=host", "expiry_time": "2021-11-07T04:06:18.165Z"}}]}, "Love ❤️": {"id": "p%3F%60~", "type": "checkbox", "checkbox": false}, "Material": {"id": "qqXe", "type": "multi_select", "multi_select": [{"id": "3be7ef6d-d58c-48d3-8426-f88584c4f013", "name": "cotton  🌱", "color": "default"}]}, "Pairing": {"id": "uoMj", "type": "rich_text", "rich_text": [{"type": "text", "text": {"content": "idk", "link": null}, "annotations": {"bold": false, "italic": false, "strikethrough": false, "underline": false, "code": false, "color": "default"}, "plain_text": "idk", "href": null}]}, "Name": {"id": "title", "type": "title", "title": [{"type": "text", "text": {"content": "pink tank top", "link": null}, "annotations": {"bold": false, "italic": false, "strikethrough": false, "underline": false, "code": false, "color": "default"}, "plain_text": "pink tank top", "href": null}]}}, "url": "https://www.notion.so/pink-tank-top-da6b77aa34184bc799c13a4852df7e42"}, {"object": "page", "id": "8452c0c4-b915-471c-9f2e-172171af5c33", "created_time": "2021-11-06T18:33:00.000Z", "last_edited_time": "2021-11-07T02:42:00.000Z", "cover": null, "icon": null, "parent": {"type": "database_id", "database_id": "52086760-ffa9-405a-ade3-a6b00bad1834"}, "archived": false, "properties": {"# worn": {"id": "B%3DFg", "type": "number", "number": 0}, "Not so much 💔": {"id": "G%3Ar%3D", "type": "checkbox", "checkbox": false}, "Brand": {"id": "IhVC", "type": "multi_select", "multi_select": [{"id": "ce49bd64-7c71-4e9c-b22f-e150ec530652", "name": "thrifted 🌱", "color": "green"}]}, "Occasion": {"id": "PbHh", "type": "multi_select", "multi_select": [{"id": "31223c61-7f7a-4418-8f92-d82dee0dd3f7", "name": "work", "color": "blue"}, {"id": "71b4c590-a3bd-427a-821d-e4b87ddab06d", "name": "cute", "color": "orange"}, {"id": "a2f57cee-d198-45b4-a451-778e7eecb804", "name": "versatile", "color": "green"}]}, "Color": {"id": "%5B%3D%7B%3F", "type": "multi_select", "multi_select": [{"id": "f5d7d333-3ce7-4dff-81ba-bbe0ec012e71", "name": "black", "color": "pink"}]}, "Photo": {"id": "l%5DHF", "type": "files", "files": [{"name": "black cotton straight pants.png", "type": "file", "file": {"url": "https://s3.us-west-2.amazonaws.com/secure.notion-static.com/e2faf2c5-7010-4d51-a8ca-5bbfc058964c/black_cotton_straight_pants.png?X-Amz-Algorithm=AWS4-HMAC-SHA256&X-Amz-Credential=AKIAT73L2G45O3KS52Y5%2F20211107%2Fus-west-2%2Fs3%2Faws4_request&X-Amz-Date=20211107T030618Z&X-Amz-Expires=3600&X-Amz-Signature=623854641df4ee8aaaa41123009f5e2ed73be7cf0869d51b67d08b8c48a4297c&X-Amz-SignedHeaders=host", "expiry_time": "2021-11-07T04:06:18.169Z"}}]}, "Love ❤️": {"id": "p%3F%60~", "type": "checkbox", "checkbox": false}, "Material": {"id": "qqXe", "type": "multi_select", "multi_select": [{"id": "3be7ef6d-d58c-48d3-8426-f88584c4f013", "name": "cotton  🌱", "color": "default"}]}, "Pairing": {"id": "uoMj", "type": "rich_text", "rich_text": [{"type": "text", "text": {"content": "black tank top", "link": null}, "annotations": {"bold": false, "italic": false, "strikethrough": false, "underline": false, "code": false, "color": "default"}, "plain_text": "black tank top", "href": null}]}, "Name": {"id": "title", "type": "title", "title": [{"type": "text", "text": {"content": "black cotton straight pants", "link": null}, "annotations": {"bold": false, "italic": false, "strikethrough": false, "underline": false, "code": false, "color": "default"}, "plain_text": "black cotton straight pants", "href": null}]}}, "url": "https://www.notion.so/black-cotton-straight-pants-8452c0c4b915471c9f2e172171af5c33"}, {"object": "page", "id": "6518e344-7a1f-4ba5-8d9a-defc22b51997", "created_time": "2021-11-06T18:31:00.000Z", "last_edited_time": "2021-11-07T01:59:00.000Z", "cover": null, "icon": null, "parent": {"type": "database_id", "database_id": "52086760-ffa9-405a-ade3-a6b00bad1834"}, "archived": false, "properties": {"# worn": {"id": "B%3DFg", "type": "number", "number": 0}, "Not so much 💔": {"id": "G%3Ar%3D", "type": "checkbox", "checkbox": false}, "Brand": {"id": "IhVC", "type": "multi_select", "multi_select": [{"id": "3d9c4fa4-9c0c-4349-8344-617ef207c18d", "name": "Dynamite", "color": "blue"}]}, "Occasion": {"id": "PbHh", "type": "multi_select", "multi_select": [{"id": "71b4c590-a3bd-427a-821d-e4b87ddab06d", "name": "cute", "color": "orange"}, {"id": "a2f57cee-d198-45b4-a451-778e7eecb804", "name": "versatile", "color": "green"}, {"id": "31223c61-7f7a-4418-8f92-d82dee0dd3f7", "name": "work", "color": "blue"}]}, "Color": {"id": "%5B%3D%7B%3F", "type": "multi_select", "multi_select": [{"id": "f5d7d333-3ce7-4dff-81ba-bbe0ec012e71", "name": "black", "color": "pink"}]}, "Photo": {"id": "l%5DHF", "type": "files", "files": [{"name": "black straight legging pants.png", "type": "file", "file": {"url": "https://s3.us-west-2.amazonaws.com/secure.notion-static.com/d81b6404-c9cb-4ae8-bf81-bdc7f6b416aa/black_straight_legging_pants.png?X-Amz-Algorithm=AWS4-HMAC-SHA256&X-Amz-Credential=AKIAT73L2G45O3KS52Y5%2F20211107%2Fus-west-2%2Fs3%2Faws4_request&X-Amz-Date=20211107T030618Z&X-Amz-Expires=3600&X-Amz-Signature=f6a367f135270775b3c0b6fd707836487fc9c6925a1436806bbfefd381114e1d&X-Amz-SignedHeaders=host", "expiry_time": "2021-11-07T04:06:18.166Z"}}]}, "Love ❤️": {"id": "p%3F%60~", "type": "checkbox", "checkbox": false}, "Material": {"id": "qqXe", "type": "multi_select", "multi_select": [{"id": "62ff4d81-20c2-4076-a4bb-1dee408cbbe1", "name": "polyester", "color": "blue"}]}, "Pairing": {"id": "uoMj", "type": "rich_text", "rich_text": [{"type": "text", "text": {"content": "idk", "link": null}, "annotations": {"bold": false, "italic": false, "strikethrough": false, "underline": false, "code": false, "color": "default"}, "plain_text": "idk", "href": null}]}, "Name": {"id": "title", "type": "title", "title": [{"type": "text", "text": {"content": "black straight legging pants", "link": null}, "annotations": {"bold": false, "italic": false, "strikethrough": false, "underline": false, "code": false, "color": "default"}, "plain_text": "black straight legging pants", "href": null}]}}, "url": "https://www.notion.so/black-straight-legging-pants-6518e3447a1f4ba58d9adefc22b51997"}, {"object": "page", "id": "e2e8d634-2558-4ce0-9d6c-edb0cd8d8881", "created_time": "2021-11-06T18:30:00.000Z", "last_edited_time": "2021-11-07T01:59:00.000Z", "cover": null, "icon": null, "parent": {"type": "database_id", "database_id": "52086760-ffa9-405a-ade3-a6b00bad1834"}, "archived": false, "properties": {"# worn": {"id": "B%3DFg", "type": "number", "number": 0}, "Not so much 💔": {"id": "G%3Ar%3D", "type": "checkbox", "checkbox": false}, "Brand": {"id": "IhVC", "type": "multi_select", "multi_select": [{"id": "c31f5407-26b6-4335-ae50-21a11c47e117", "name": "Zara", "color": "yellow"}]}, "Occasion": {"id": "PbHh", "type": "multi_select", "multi_select": [{"id": "71b4c590-a3bd-427a-821d-e4b87ddab06d", "name": "cute", "color": "orange"}, {"id": "f480f01c-b765-47c9-9198-ec2601cf2ba4", "name": "out", "color": "red"}, {"id": "4a2ef721-6f0b-4163-bee2-bd4239d74343", "name": "summer", "color": "pink"}, {"id": "90ff855f-196a-4d12-ab5e-e969a34cd3bb", "name": "spring", "color": "green"}]}, "Color": {"id": "%5B%3D%7B%3F", "type": "multi_select", "multi_select": [{"id": "b3e79d42-568b-40a4-9db0-a6434b820c3b", "name": "grey", "color": "red"}, {"id": "f5d7d333-3ce7-4dff-81ba-bbe0ec012e71", "name": "black", "color": "pink"}]}, "Photo": {"id": "l%5DHF", "type": "files", "files": [{"name": "midi snake print skirt.png", "type": "file", "file": {"url": "https://s3.us-west-2.amazonaws.com/secure.notion-static.com/d6736002-bcd2-4e94-85e4-abfa249df51e/midi_snake_print_skirt.png?X-Amz-Algorithm=AWS4-HMAC-SHA256&X-Amz-Credential=AKIAT73L2G45O3KS52Y5%2F20211107%2Fus-west-2%2Fs3%2Faws4_request&X-Amz-Date=20211107T030618Z&X-Amz-Expires=3600&X-Amz-Signature=84d4ca8cfc41c40b074637fd17b3e2821009dd0e1abd10fe7651d09ad4b78df0&X-Amz-SignedHeaders=host", "expiry_time": "2021-11-07T04:06:18.168Z"}}]}, "Love ❤️": {"id": "p%3F%60~", "type": "checkbox", "checkbox": false}, "Material": {"id": "qqXe", "type": "multi_select", "multi_select": [{"id": "62ff4d81-20c2-4076-a4bb-1dee408cbbe1", "name": "polyester", "color": "blue"}]}, "Pairing": {"id": "uoMj", "type": "rich_text", "rich_text": [{"type": "text", "text": {"content": "idk", "link": null}, "annotations": {"bold": false, "italic": false, "strikethrough": false, "underline": false, "code": false, "color": "default"}, "plain_text": "idk", "href": null}]}, "Name": {"id": "title", "type": "title", "title": [{"type": "text", "text": {"content": "midi snake print skirt", "link": null}, "annotations": {"bold": false, "italic": false, "strikethrough": false, "underline": false, "code": false, "color": "default"}, "plain_text": "midi snake print skirt", "href": null}]}}, "url": "https://www.notion.so/midi-snake-print-skirt-e2e8d63425584ce09d6cedb0cd8d8881"}, {"object": "page", "id": "0479ba8e-cb6e-4466-8fc8-b03e25afd1b2", "created_time": "2021-11-06T18:28:00.000Z", "last_edited_time": "2021-11-07T02:42:00.000Z", "cover": null, "icon": null, "parent": {"type": "database_id", "database_id": "52086760-ffa9-405a-ade3-a6b00bad1834"}, "archived": false, "properties": {"# worn": {"id": "B%3DFg", "type": "number", "number": 0}, "Not so much 💔": {"id": "G%3Ar%3D", "type": "checkbox", "checkbox": false}, "Brand": {"id": "IhVC", "type": "multi_select", "multi_select": [{"id": "ce49bd64-7c71-4e9c-b22f-e150ec530652", "name": "thrifted 🌱", "color": "green"}]}, "Occasion": {"id": "PbHh", "type": "multi_select", "multi_select": [{"id": "4a2ef721-6f0b-4163-bee2-bd4239d74343", "name": "summer", "color": "pink"}, {"id": "71b4c590-a3bd-427a-821d-e4b87ddab06d", "name": "cute", "color": "orange"}, {"id": "90ff855f-196a-4d12-ab5e-e969a34cd3bb", "name": "spring", "color": "green"}]}, "Color": {"id": "%5B%3D%7B%3F", "type": "multi_select", "multi_select": [{"id": "QJ[S", "name": "navy blue", "color": "default"}]}, "Photo": {"id": "l%5DHF", "type": "files", "files": [{"name": "jean skirt.png", "type": "file", "file": {"url": "https://s3.us-west-2.amazonaws.com/secure.notion-static.com/80060cf0-f405-4f1f-8377-267cd029f59d/jean_skirt.png?X-Amz-Algorithm=AWS4-HMAC-SHA256&X-Amz-Credential=AKIAT73L2G45O3KS52Y5%2F20211107%2Fus-west-2%2Fs3%2Faws4_request&X-Amz-Date=20211107T030618Z&X-Amz-Expires=3600&X-Amz-Signature=1ba75b03e10e5ea5006a72d83c3384b96fec6d67e1a4d68a0dd2bd93a0d6405c&X-Amz-SignedHeaders=host", "expiry_time": "2021-11-07T04:06:18.166Z"}}]}, "Love ❤️": {"id": "p%3F%60~", "type": "checkbox", "checkbox": false}, "Material": {"id": "qqXe", "type": "multi_select", "multi_select": [{"id": "f0cb205a-a359-42ba-90e1-97f1e7fb0d05", "name": "denim", "color": "purple"}]}, "Pairing": {"id": "uoMj", "type": "rich_text", "rich_text": [{"type": "text", "text": {"content": "black and white t-shirt", "link": null}, "annotations": {"bold": false, "italic": false, "strikethrough": false, "underline": false, "code": false, "color": "default"}, "plain_text": "black and white t-shirt", "href": null}]}, "Name": {"id": "title", "type": "title", "title": [{"type": "text", "text": {"content": "jean skirt", "link": null}, "annotations": {"bold": false, "italic": false, "strikethrough": false, "underline": false, "code": false, "color": "default"}, "plain_text": "jean skirt", "href": null}]}}, "url": "https://www.notion.so/jean-skirt-0479ba8ecb6e44668fc8b03e25afd1b2"}, {"object": "page", "id": "56ec170b-d231-4c28-811a-34e91d546bde", "created_time": "2021-11-06T18:26:00.000Z", "last_edited_time": "2021-11-07T01:59:00.000Z", "cover": null, "icon": null, "parent": {"type": "database_id", "database_id": "52086760-ffa9-405a-ade3-a6b00bad1834"}, "archived": false, "properties": {"# worn": {"id": "B%3DFg", "type": "number", "number": 0}, "Not so much 💔": {"id": "G%3Ar%3D", "type": "checkbox", "checkbox": false}, "Brand": {"id": "IhVC", "type": "multi_select", "multi_select": [{"id": "38d01367-2205-4d1f-a6af-6403417af5ff", "name": "H&M", "color": "pink"}]}, "Occasion": {"id": "PbHh", "type": "multi_select", "multi_select": [{"id": "71b4c590-a3bd-427a-821d-e4b87ddab06d", "name": "cute", "color": "orange"}, {"id": "f480f01c-b765-47c9-9198-ec2601cf2ba4", "name": "out", "color": "red"}, {"id": "a2f57cee-d198-45b4-a451-778e7eecb804", "name": "versatile", "color": "green"}, {"id": "91582190-1742-440c-9abd-02ccb47aff29", "name": "fall", "color": "brown"}, {"id": "daa6d8bd-0e9d-4952-9c47-8b1d1808dbab", "name": "winter", "color": "gray"}]}, "Color": {"id": "%5B%3D%7B%3F", "type": "multi_select", "multi_select": [{"id": "f5d7d333-3ce7-4dff-81ba-bbe0ec012e71", "name": "black", "color": "pink"}, {"id": "372a84e9-d449-4d9e-b18a-32efa8fb0ef7", "name": "white", "color": "blue"}, {"id": "d482328e-c562-4e70-a636-f39dcf77a8f2", "name": "beige", "color": "default"}]}, "Photo": {"id": "l%5DHF", "type": "files", "files": [{"name": "tweed mini skirt.png", "type": "file", "file": {"url": "https://s3.us-west-2.amazonaws.com/secure.notion-static.com/34f69054-6c75-46bd-bfb8-b466c9ca8720/tweed_mini_skirt.png?X-Amz-Algorithm=AWS4-HMAC-SHA256&X-Amz-Credential=AKIAT73L2G45O3KS52Y5%2F20211107%2Fus-west-2%2Fs3%2Faws4_request&X-Amz-Date=20211107T030618Z&X-Amz-Expires=3600&X-Amz-Signature=96e6cf3ba9557abc0645c18f42ae37ee714628b2b340d3afdeba124e8ff7da11&X-Amz-SignedHeaders=host", "expiry_time": "2021-11-07T04:06:18.164Z"}}]}, "Love ❤️": {"id": "p%3F%60~", "type": "checkbox", "checkbox": true}, "Material": {"id": "qqXe", "type": "multi_select", "multi_select": [{"id": "0f4af3b9-bac7-49cd-b501-b0e38a792fe7", "name": "wool 🌱", "color": "pink"}]}, "Pairing": {"id": "uoMj", "type": "rich_text", "rich_text": [{"type": "text", "text": {"content": "idk", "link": null}, "annotations": {"bold": false, "italic": false, "strikethrough": false, "underline": false, "code": false, "color": "default"}, "plain_text": "idk", "href": null}]}, "Name": {"id": "title", "type": "title", "title": [{"type": "text", "text": {"content": "tweed mini skirt", "link": null}, "annotations": {"bold": false, "italic": false, "strikethrough": false, "underline": false, "code": false, "color": "default"}, "plain_text": "tweed mini skirt", "href": null}]}}, "url": "https://www.notion.so/tweed-mini-skirt-56ec170bd2314c28811a34e91d546bde"}, {"object": "page", "id": "fdb6766b-e6e4-4d57-b3ce-0695477a6908", "created_time": "2021-11-06T18:20:00.000Z", "last_edited_time": "2021-11-07T01:59:00.000Z", "cover": null, "icon": null, "parent": {"type": "database_id", "database_id": "52086760-ffa9-405a-ade3-a6b00bad1834"}, "archived": false, "properties": {"# worn": {"id": "B%3DFg", "type": "number", "number": 0}, "Not so much 💔": {"id": "G%3Ar%3D", "type": "checkbox", "checkbox": false}, "Brand": {"id": "IhVC", "type": "multi_select", "multi_select": [{"id": "c31f5407-26b6-4335-ae50-21a11c47e117", "name": "Zara", "color": "yellow"}]}, "Occasion": {"id": "PbHh", "type": "multi_select", "multi_select": [{"id": "f480f01c-b765-47c9-9198-ec2601cf2ba4", "name": "out", "color": "red"}]}, "Color": {"id": "%5B%3D%7B%3F", "type": "multi_select", "multi_select": [{"id": "e816ffbd-4c0a-4667-a3e7-8a1169be47d8", "name": "light pink", "color": "brown"}]}, "Photo": {"id": "l%5DHF", "type": "files", "files": [{"name": "light pink bodysuit.png", "type": "file", "file": {"url": "https://s3.us-west-2.amazonaws.com/secure.notion-static.com/594727ee-8135-4557-9abf-1e157bcbb9d6/light_pink_bodysuit.png?X-Amz-Algorithm=AWS4-HMAC-SHA256&X-Amz-Credential=AKIAT73L2G45O3KS52Y5%2F20211107%2Fus-west-2%2Fs3%2Faws4_request&X-Amz-Date=20211107T030618Z&X-Amz-Expires=3600&X-Amz-Signature=498d6563ae79edf89a8d182205bfc5ac892eeb659cc2937758a58487b8bab298&X-Amz-SignedHeaders=host", "expiry_time": "2021-11-07T04:06:18.162Z"}}]}, "Love ❤️": {"id": "p%3F%60~", "type": "checkbox", "checkbox": false}, "Material": {"id": "qqXe", "type": "multi_select", "multi_select": [{"id": "62ff4d81-20c2-4076-a4bb-1dee408cbbe1", "name": "polyester", "color": "blue"}]}, "Pairing": {"id": "uoMj", "type": "rich_text", "rich_text": [{"type": "text", "text": {"content": "idk", "link": null}, "annotations": {"bold": false, "italic": false, "strikethrough": false, "underline": false, "code": false, "color": "default"}, "plain_text": "idk", "href": null}]}, "Name": {"id": "title", "type": "title", "title": [{"type": "text", "text": {"content": "light pink bodysuit", "link": null}, "annotations": {"bold": false, "italic": false, "strikethrough": false, "underline": false, "code": false, "color": "default"}, "plain_text": "light pink bodysuit", "href": null}]}}, "url": "https://www.notion.so/light-pink-bodysuit-fdb6766be6e44d57b3ce0695477a6908"}, {"object": "page", "id": "a1c2f222-bc64-464b-80a1-96d688819f23", "created_time": "2021-11-06T17:57:00.000Z", "last_edited_time": "2021-11-07T01:59:00.000Z", "cover": null, "icon": null, "parent": {"type": "database_id", "database_id": "52086760-ffa9-405a-ade3-a6b00bad1834"}, "archived": false, "properties": {"# worn": {"id": "B%3DFg", "type": "number", "number": 0}, "Not so much 💔": {"id": "G%3Ar%3D", "type": "checkbox", "checkbox": false}, "Brand": {"id": "IhVC", "type": "multi_select", "multi_select": [{"id": "Jgu=", "name": "Aeropostale", "color": "default"}]}, "Occasion": {"id": "PbHh", "type": "multi_select", "multi_select": [{"id": "71b4c590-a3bd-427a-821d-e4b87ddab06d", "name": "cute", "color": "orange"}, {"id": "4a2ef721-6f0b-4163-bee2-bd4239d74343", "name": "summer", "color": "pink"}, {"id": "d4e44d9a-818b-43ad-ab40-83992bec63df", "name": "chill", "color": "purple"}]}, "Color": {"id": "%5B%3D%7B%3F", "type": "multi_select", "multi_select": [{"id": "QJ[S", "name": "navy blue", "color": "default"}]}, "Photo": {"id": "l%5DHF", "type": "files", "files": [{"name": "blue west cost tank.png", "type": "file", "file": {"url": "https://s3.us-west-2.amazonaws.com/secure.notion-static.com/50cec9e1-9e08-4b13-b1d2-c895c334540a/blue_west_cost_tank.png?X-Amz-Algorithm=AWS4-HMAC-SHA256&X-Amz-Credential=AKIAT73L2G45O3KS52Y5%2F20211107%2Fus-west-2%2Fs3%2Faws4_request&X-Amz-Date=20211107T030618Z&X-Amz-Expires=3600&X-Amz-Signature=8870820c5c1e221590bcc6a9bb581cec90f4bb48a277049a7dcbaacf96334953&X-Amz-SignedHeaders=host", "expiry_time": "2021-11-07T04:06:18.167Z"}}]}, "Love ❤️": {"id": "p%3F%60~", "type": "checkbox", "checkbox": false}, "Material": {"id": "qqXe", "type": "multi_select", "multi_select": [{"id": "62ff4d81-20c2-4076-a4bb-1dee408cbbe1", "name": "polyester", "color": "blue"}, {"id": "3be7ef6d-d58c-48d3-8426-f88584c4f013", "name": "cotton  🌱", "color": "default"}]}, "Pairing": {"id": "uoMj", "type": "rich_text", "rich_text": [{"type": "text", "text": {"content": "idk", "link": null}, "annotations": {"bold": false, "italic": false, "strikethrough": false, "underline": false, "code": false, "color": "default"}, "plain_text": "idk", "href": null}]}, "Name": {"id": "title", "type": "title", "title": [{"type": "text", "text": {"content": "blue west coast tank", "link": null}, "annotations": {"bold": false, "italic": false, "strikethrough": false, "underline": false, "code": false, "color": "default"}, "plain_text": "blue west coast tank", "href": null}]}}, "url": "https://www.notion.so/blue-west-coast-tank-a1c2f222bc64464b80a196d688819f23"}, {"object": "page", "id": "7cfa5463-5125-4d28-9c51-7dfe0990dee3", "created_time": "2021-11-06T17:43:00.000Z", "last_edited_time": "2021-11-07T02:42:00.000Z", "cover": null, "icon": null, "parent": {"type": "database_id", "database_id": "52086760-ffa9-405a-ade3-a6b00bad1834"}, "archived": false, "properties": {"# worn": {"id": "B%3DFg", "type": "number", "number": 0}, "Not so much 💔": {"id": "G%3Ar%3D", "type": "checkbox", "checkbox": false}, "Brand": {"id": "IhVC", "type": "multi_select", "multi_select": [{"id": "857e166e-1a6f-4f1e-b8bd-cf2b71f610f6", "name": "kotn 🌱", "color": "orange"}]}, "Occasion": {"id": "PbHh", "type": "multi_select", "multi_select": [{"id": "71b4c590-a3bd-427a-821d-e4b87ddab06d", "name": "cute", "color": "orange"}, {"id": "d4e44d9a-818b-43ad-ab40-83992bec63df", "name": "chill", "color": "purple"}, {"id": "4a2ef721-6f0b-4163-bee2-bd4239d74343", "name": "summer", "color": "pink"}, {"id": "a2f57cee-d198-45b4-a451-778e7eecb804", "name": "versatile", "color": "green"}]}, "Color": {"id": "%5B%3D%7B%3F", "type": "multi_select", "multi_select": [{"id": "f5d7d333-3ce7-4dff-81ba-bbe0ec012e71", "name": "black", "color": "pink"}]}, "Photo": {"id": "l%5DHF", "type": "files", "files": [{"name": "black tank top.png", "type": "file", "file": {"url": "https://s3.us-west-2.amazonaws.com/secure.notion-static.com/23922aa3-40dc-4aab-af13-402fc8aaf8a4/black_tank_top.png?X-Amz-Algorithm=AWS4-HMAC-SHA256&X-Amz-Credential=AKIAT73L2G45O3KS52Y5%2F20211107%2Fus-west-2%2Fs3%2Faws4_request&X-Amz-Date=20211107T030618Z&X-Amz-Expires=3600&X-Amz-Signature=08beb24bd03a65779ef3829d519e7381d33b8e50aa7ffa3bc04de52a1d15d613&X-Amz-SignedHeaders=host", "expiry_time": "2021-11-07T04:06:18.164Z"}}]}, "Love ❤️": {"id": "p%3F%60~", "type": "checkbox", "checkbox": false}, "Material": {"id": "qqXe", "type": "multi_select", "multi_select": [{"id": "3be7ef6d-d58c-48d3-8426-f88584c4f013", "name": "cotton  🌱", "color": "default"}]}, "Pairing": {"id": "uoMj", "type": "rich_text", "rich_text": [{"type": "text", "text": {"content": "black cotton straight pants", "link": null}, "annotations": {"bold": false, "italic": false, "strikethrough": false, "underline": false, "code": false, "color": "default"}, "plain_text": "black cotton straight pants", "href": null}]}, "Name": {"id": "title", "type": "title", "title": [{"type": "text", "text": {"content": "black tank top", "link": null}, "annotations": {"bold": false, "italic": false, "strikethrough": false, "underline": false, "code": false, "color": "default"}, "plain_text": "black tank top", "href": null}]}}, "url": "https://www.notion.so/black-tank-top-7cfa546351254d289c517dfe0990dee3"}, {"object": "page", "id": "7f3f0000-b553-49f4-8ca2-e5b12eada9e4", "created_time": "2021-11-06T17:43:00.000Z", "last_edited_time": "2021-11-07T02:42:00.000Z", "cover": null, "icon": null, "parent": {"type": "database_id", "database_id": "52086760-ffa9-405a-ade3-a6b00bad1834"}, "archived": false, "properties": {"# worn": {"id": "B%3DFg", "type": "number", "number": 0}, "Not so much 💔": {"id": "G%3Ar%3D", "type": "checkbox", "checkbox": false}, "Brand": {"id": "IhVC", "type": "multi_select", "multi_select": [{"id": "55ef5e9d-8bad-478d-82c9-2f0cc9a9c787", "name": "Aritzia", "color": "default"}]}, "Occasion": {"id": "PbHh", "type": "multi_select", "multi_select": [{"id": "71b4c590-a3bd-427a-821d-e4b87ddab06d", "name": "cute", "color": "orange"}, {"id": "c1cbee17-cb59-435e-828c-219e70f8fe0c", "name": "swimsuit coverup", "color": "default"}]}, "Color": {"id": "%5B%3D%7B%3F", "type": "multi_select", "multi_select": [{"id": "372a84e9-d449-4d9e-b18a-32efa8fb0ef7", "name": "white", "color": "blue"}]}, "Photo": {"id": "l%5DHF", "type": "files", "files": [{"name": "white long sleeve crop top.png", "type": "file", "file": {"url": "https://s3.us-west-2.amazonaws.com/secure.notion-static.com/6d13a5a6-4d58-4eea-9afe-d5aef608fbc9/white_long_sleeve_crop_top.png?X-Amz-Algorithm=AWS4-HMAC-SHA256&X-Amz-Credential=AKIAT73L2G45O3KS52Y5%2F20211107%2Fus-west-2%2Fs3%2Faws4_request&X-Amz-Date=20211107T030618Z&X-Amz-Expires=3600&X-Amz-Signature=0d4fb008aaee3b098f5fcb52415651f41afe561763558df676e813590f25a5a8&X-Amz-SignedHeaders=host", "expiry_time": "2021-11-07T04:06:18.163Z"}}]}, "Love ❤️": {"id": "p%3F%60~", "type": "checkbox", "checkbox": false}, "Material": {"id": "qqXe", "type": "multi_select", "multi_select": [{"id": "3be7ef6d-d58c-48d3-8426-f88584c4f013", "name": "cotton  🌱", "color": "default"}, {"id": "62ff4d81-20c2-4076-a4bb-1dee408cbbe1", "name": "polyester", "color": "blue"}]}, "Pairing": {"id": "uoMj", "type": "rich_text", "rich_text": [{"type": "text", "text": {"content": "idk", "link": null}, "annotations": {"bold": false, "italic": false, "strikethrough": false, "underline": false, "code": false, "color": "default"}, "plain_text": "idk", "href": null}]}, "Name": {"id": "title", "type": "title", "title": [{"type": "text", "text": {"content": "white long sleeve crop top", "link": null}, "annotations": {"bold": false, "italic": false, "strikethrough": false, "underline": false, "code": false, "color": "default"}, "plain_text": "white long sleeve crop top", "href": null}]}}, "url": "https://www.notion.so/white-long-sleeve-crop-top-7f3f0000b55349f48ca2e5b12eada9e4"}, {"object": "page", "id": "9732f976-bef7-454b-b1d4-3dac4f33c79f", "created_time": "2021-11-06T17:43:00.000Z", "last_edited_time": "2021-11-07T03:04:00.000Z", "cover": null, "icon": null, "parent": {"type": "database_id", "database_id": "52086760-ffa9-405a-ade3-a6b00bad1834"}, "archived": false, "properties": {"# worn": {"id": "B%3DFg", "type": "number", "number": 0}, "Not so much 💔": {"id": "G%3Ar%3D", "type": "checkbox", "checkbox": false}, "Brand": {"id": "IhVC", "type": "multi_select", "multi_select": [{"id": "702af932-e58b-4929-abed-5e558a2b4f60", "name": "Garage", "color": "brown"}]}, "Occasion": {"id": "PbHh", "type": "multi_select", "multi_select": [{"id": "71b4c590-a3bd-427a-821d-e4b87ddab06d", "name": "cute", "color": "orange"}, {"id": "d4e44d9a-818b-43ad-ab40-83992bec63df", "name": "chill", "color": "purple"}, {"id": "91582190-1742-440c-9abd-02ccb47aff29", "name": "fall", "color": "brown"}, {"id": "4a2ef721-6f0b-4163-bee2-bd4239d74343", "name": "summer", "color": "pink"}, {"id": "31223c61-7f7a-4418-8f92-d82dee0dd3f7", "name": "work", "color": "blue"}]}, "Color": {"id": "%5B%3D%7B%3F", "type": "multi_select", "multi_select": [{"id": "f5d7d333-3ce7-4dff-81ba-bbe0ec012e71", "name": "black", "color": "pink"}, {"id": "372a84e9-d449-4d9e-b18a-32efa8fb0ef7", "name": "white", "color": "blue"}]}, "Photo": {"id": "l%5DHF", "type": "files", "files": [{"name": "black and white t-shirt.png", "type": "file", "file": {"url": "https://s3.us-west-2.amazonaws.com/secure.notion-static.com/b3bc601a-f43b-4827-831f-9b9c5d6f75ae/black_and_white_t-shirt.png?X-Amz-Algorithm=AWS4-HMAC-SHA256&X-Amz-Credential=AKIAT73L2G45O3KS52Y5%2F20211107%2Fus-west-2%2Fs3%2Faws4_request&X-Amz-Date=20211107T030618Z&X-Amz-Expires=3600&X-Amz-Signature=518d8d25c7a74b923a0a0cffd756eefb9c67f4e045dcf4f29ecc662315f82390&X-Amz-SignedHeaders=host", "expiry_time": "2021-11-07T04:06:18.163Z"}}]}, "Love ❤️": {"id": "p%3F%60~", "type": "checkbox", "checkbox": false}, "Material": {"id": "qqXe", "type": "multi_select", "multi_select": [{"id": "1ad3bb98-d196-4909-8efa-da6b7508f3fe", "name": "rayon", "color": "gray"}]}, "Pairing": {"id": "uoMj", "type": "rich_text", "rich_text": [{"type": "text", "text": {"content": "jean skirt", "link": null}, "annotations": {"bold": false, "italic": false, "strikethrough": false, "underline": false, "code": false, "color": "default"}, "plain_text": "jean skirt", "href": null}]}, "Name": {"id": "title", "type": "title", "title": [{"type": "text", "text": {"content": "black and white t-shirt", "link": null}, "annotations": {"bold": false, "italic": false, "strikethrough": false, "underline": false, "code": false, "color": "default"}, "plain_text": "black and white t-shirt", "href": null}]}}, "url": "https://www.notion.so/black-and-white-t-shirt-9732f976bef7454bb1d43dac4f33c79f"}], "next_cursor": null, "has_more": false}